[{"url":"https:\/\/www.youtube.com\/watch?v=3xD9pHroECQ","title":"Beatbox Tutorial Tuesday EP 3 pt 1: Hum & Beatbox at the Same Time","channel":"80Fitz\u00a0","sound":"Humming and Beatboxing","difficulty":"Intermediate"},{"url":"https:\/\/www.youtube.com\/watch?v=cet6p1v4kHI","title":"Tutorial #4: Humming+Beatboxing || Drop It Like Its Hot Tutorial || Beatbox Tutorial Series","channel":"The Orthobox","sound":"Humming and Beatboxing","difficulty":"Intermediate"},{"url":"https:\/\/www.youtube.com\/watch?v=VasrL5HJ3oU","title":"HOW TO BEATBOX #2 (Hum and Beatbox at the Same Time)","channel":"SoCloseToToast\u00a0","sound":"Humming and Beatboxing","difficulty":"Intermediate"},{"url":"https:\/\/www.youtube.com\/watch?v=RRYHW4ONgx8","title":"How to Beatbox and hum at the same time! TUTORIAL","channel":"Tricksandbeats","sound":"Humming and Beatboxing","difficulty":"Intermediate"},{"url":"https:\/\/www.youtube.com\/watch?v=PxsprXrOANw","title":"Beatbox tutorial - Humming whilst beatboxing","channel":"Fat Tony","sound":"Humming and Beatboxing","difficulty":"Intermediate"},{"url":"https:\/\/www.youtube.com\/watch?v=6An9y-5Qacs","title":"Beatbox Tutorial Episode 19: Singing and Beatboxing AT THE SAME TIME!","channel":"Beatbox Tutorials","sound":"Humming and Beatboxing","difficulty":"Intermediate"},{"url":"https:\/\/www.youtube.com\/watch?v=6mVT0SyXAxM","title":"Beatbox Tutorial 5 | Humming while beatboxing! + Practice beat","channel":"ACEGamer9","sound":"Humming and Beatboxing","difficulty":"Intermediate"},{"url":"https:\/\/www.youtube.com\/watch?v=zKOFqebG0fk","title":"Beatbox Tutorial Tuesday EP 3 pt 2: Hum & Beatbox at the Same Time","channel":"80Fitz\u00a0","sound":"Humming and Beatboxing","difficulty":"Intermediate"},{"url":"https:\/\/www.youtube.com\/watch?v=spexsYFP1ME","title":"Beatbox tutorial 3 - Humming and Beatboxing","channel":"DaRevolutionist8","sound":"Humming and Beatboxing","difficulty":"Intermediate"},{"url":"https:\/\/www.youtube.com\/watch?v=Bfmv3kTmYR8","title":"How to - Basic Beatbox Tutorial - B T K - Binibining Beats","channel":"Binibining Beats","sound":"Humming and Beatboxing","difficulty":"Intermediate"},{"url":"https:\/\/www.youtube.com\/watch?v=yPeuw72dfLc","title":"How to hum while beatboxing!","channel":"A Lunch Trey","sound":"Humming and Beatboxing","difficulty":"Intermediate"},{"url":"https:\/\/www.youtube.com\/watch?v=8rqhmP9t1t8","title":"Teaching You Singing and Humming While Beatboxing!","channel":"Paige Zilba","sound":"Humming and Beatboxing","difficulty":"Intermediate"},{"url":"https:\/\/www.youtube.com\/watch?v=XT40OP7tVUE","title":"Humming Bass Kick and Snare Beatbox Tutorial","channel":"Puissance","sound":"Humming and Beatboxing","difficulty":"Intermediate"},{"url":"https:\/\/www.youtube.com\/watch?v=um-NWi4RcOU","title":"HUMMING BEATBOX TUTORIAL","channel":"BeatboxR - Tutorials, Reactions & more","sound":"Humming and Beatboxing","difficulty":"Intermediate"},{"url":"https:\/\/www.youtube.com\/watch?v=kyTaFlIEwTo","title":"Tutorial #1: Basic Sounds of Beatbox || Beatbox Tutorial Series: YOU Can Beatbox","channel":"The Orthobox","sound":"Humming and Beatboxing","difficulty":"Intermediate"},{"url":"https:\/\/www.youtube.com\/watch?v=wXwzS1LlACw","title":"How to hum while beatboxing ?-beatbox tutorial#2 by EF-Fusion","channel":"EF-Fusion BeatBox","sound":"Humming and Beatboxing","difficulty":"Intermediate"},{"url":"https:\/\/www.youtube.com\/watch?v=_e5IOEHFzxo","title":"Tutorial #35: Trap Hi Hats || YOU Can Beatbox","channel":"The Orthobox","sound":"Trap Hi-Hat","difficulty":"Intermediate"},{"url":"https:\/\/www.youtube.com\/watch?v=L5PnB5Ku6q4","title":"Trap\/Rolling Hi-Hat Beatbox Tutorial","channel":"Mckoy TV","sound":"Trap Hi-Hat","difficulty":"Intermediate"},{"url":"https:\/\/www.youtube.com\/watch?v=JXMlDi9iTBU","title":"TUTORIAL BEATBOX UNTUK PEMULA - TRAP HIGH HAT (ROLLING HIGH HAT)","channel":"Aan Hasibuan","sound":"Trap Hi-Hat","difficulty":"Intermediate"},{"url":"https:\/\/www.youtube.com\/watch?v=taPs7lGhrM4","title":"How to do the trap hi hat ?~BeatBox tutorial#10 by EF-Fusion","channel":"EF-Fusion BeatBox","sound":"Trap Hi-Hat","difficulty":"Intermediate"},{"url":"https:\/\/www.youtube.com\/watch?v=TnsbZpjS3Hc","title":"BEATBOX TUTORIAL - HI HAT ROLL & TRAP MUSIC","channel":"Aan Hasibuan","sound":"Trap Hi-Hat","difficulty":"Intermediate"},{"url":"https:\/\/www.youtube.com\/watch?v=WAL5tOLbhrk","title":"These are the best hi hat techniques for REAL Trap Music Tutorial","channel":"Busy Works Beats\u00a0","sound":"Trap Hi-Hat","difficulty":"Intermediate"},{"url":"https:\/\/www.youtube.com\/watch?v=C02R4W_XDkA","title":"TRAP HIGH - HAT | HINDI TUTORIAL | HOW TO BEATBOX | BEGINNERS","channel":"Yash Mittal","sound":"Trap Hi-Hat","difficulty":"Intermediate"},{"url":"https:\/\/www.youtube.com\/watch?v=B19ZKJaHamo","title":"BASIC BEATBOX TUTORIAL - HI HAT","channel":"footboxG","sound":"Trap Hi-Hat","difficulty":"Intermediate"},{"url":"https:\/\/www.youtube.com\/watch?v=SBGwm8j-lc0","title":"Vocalized Chest Bass Tutorial (Wunknown)","channel":"Wunknown Beatbox","sound":"Chest Bass","difficulty":"Intermediate"},{"url":"https:\/\/www.youtube.com\/watch?v=ONh8fP9Gtm4","title":"THROAT and CHEST Bass Tutorial | Learn Both! | Difference Explained In Depth","channel":"Cirby Beatbox","sound":"Chest Bass","difficulty":"Intermediate"},{"url":"https:\/\/www.youtube.com\/watch?v=-2vPjaPAlRA","title":"Tutorial#24 Chest Bass\/Vocalized Chest Bass | Kindo","channel":"Kindo Beats","sound":"Chest Bass","difficulty":"Intermediate"},{"url":"https:\/\/www.youtube.com\/watch?v=fyyQBXfe0zw","title":"How To Beatbox - Vibration Bass Tutorial","channel":"TylaDubya","sound":"Chest Bass","difficulty":"Intermediate"},{"url":"https:\/\/www.youtube.com\/watch?v=R04hATEWspA","title":"LEARN VOCAL CHEST BASS IN 4 MINS - BEATBOX TUTORIAL - SUBSONIC","channel":"Subsonic - Beatbox Tutorials","sound":"Chest Bass","difficulty":"Intermediate"},{"url":"https:\/\/www.youtube.com\/watch?v=JW5B_7WVy5A","title":"Beatbox Tutorial | Chest Bass (Tagalog)","channel":"Mckoy TV","sound":"Chest Bass","difficulty":"Intermediate"},{"url":"https:\/\/www.youtube.com\/watch?v=_l1LgpCXu6g","title":"Chest vibration Bass tutorial (DEEP BASS)","channel":"Hi Ro VlogYT","sound":"Chest Bass","difficulty":"Intermediate"},{"url":"https:\/\/www.youtube.com\/watch?v=L2ggRffLmVs","title":"HOW TO BEATBOX | Unique Chest\/Outward Bass Technique!","channel":"SoCloseToToast\u00a0","sound":"Chest Bass","difficulty":"Intermediate"},{"url":"https:\/\/www.youtube.com\/watch?v=9dcMYYZ8-Do","title":"BENJA | How To Do The ''Benja'' Vocalized Chest Bass | Tutorial","channel":"Benja","sound":"Chest Bass","difficulty":"Intermediate"},{"url":"https:\/\/www.youtube.com\/watch?v=LqciuL81wno","title":"VOCAL BASS TUTORIAL","channel":"pwad","sound":"Chest Bass","difficulty":"Intermediate"},{"url":"https:\/\/www.youtube.com\/watch?v=XgZCY0Kni30","title":"JAYNKINS CHEST BASS TUTORIAL \/ BEATBOX TUTORIAL","channel":"Trial Beatbox","sound":"Chest Bass","difficulty":"Intermediate"},{"url":"https:\/\/www.youtube.com\/watch?v=eF1p-r7M8xg","title":"TRUNG BAO - 20 Types of Lip Rolls","channel":"TRUNG BAO & CHIWAWA\u00a0","sound":"Chest Bass","difficulty":"Intermediate"},{"url":"https:\/\/www.youtube.com\/watch?v=XvAbhem0Y40","title":"Wunknown | Vibration Bass Tutorial","channel":"Wunknown Beatbox","sound":"Chest Bass","difficulty":"Intermediate"},{"url":"https:\/\/www.youtube.com\/watch?v=fQeeBuFfAtE","title":"High Pitch Chest Bass | Pwad High Pitch Vocal Bass","channel":"Mckoy TV","sound":"Chest Bass","difficulty":"Intermediate"},{"url":"https:\/\/www.youtube.com\/watch?v=WMObPYnVO-I","title":"Wuknown Vocalized chest bass | Tutorial de beatbox #29 | Orodreth","channel":"Orodreth","sound":"Chest Bass","difficulty":"Intermediate"},{"url":"https:\/\/www.youtube.com\/watch?v=Otb-tjzSFuk","title":"Kick Roll Beatbox Tutorial","channel":"Mckoy TV","sound":"Kick Rolls","difficulty":"Intermediate"},{"url":"https:\/\/www.youtube.com\/watch?v=cM7LG42otw4","title":"Beatbox Tutorial | Kick Roll","channel":"Nemesis Music","sound":"Kick Rolls","difficulty":"Intermediate"},{"url":"https:\/\/www.youtube.com\/watch?v=Q95VKtEnI6s","title":"Beatbox tutorial - Kick rolls","channel":"Fat Tony","sound":"Kick Rolls","difficulty":"Intermediate"},{"url":"https:\/\/www.youtube.com\/watch?v=2NmalRCS5fM","title":"KICK ROLL || VBeatbox Tutorial || Trung Bao || H\u00c6\u00b0\u00e1\u00bb\u203ang D\u00e1\u00ba\u00abn Beatbox N\u00c3\u00a2ng Cao","channel":"VBeatbox","sound":"Kick Rolls","difficulty":"Intermediate"},{"url":"https:\/\/www.youtube.com\/watch?v=91q854kLtkg","title":"Basic Technical Patterns Kick Rolls + Double Rimshot For Beginners","channel":"Mckoy TV","sound":"Kick Rolls","difficulty":"Intermediate"},{"url":"https:\/\/www.youtube.com\/watch?v=GjY9AVpGPvU","title":"NaPoM on Kick Rolls and Technicality","channel":"Vishnu Sriram","sound":"Kick Rolls","difficulty":"Intermediate"},{"url":"https:\/\/www.youtube.com\/watch?v=evxtbvyibho","title":"Kick and Hat Roll Tutorial - How To Beatbox 2020","channel":"KAO Beatbox Tutorials","sound":"Kick Rolls","difficulty":"Intermediate"},{"url":"https:\/\/www.youtube.com\/watch?v=gOrcvfhrHDc","title":"Bdb d bbd Bdb d  Kick drum training!","channel":"Helium_Beatbox","sound":"Kick Rolls","difficulty":"Intermediate"},{"url":"https:\/\/www.youtube.com\/watch?v=wUun-qxA_hQ","title":"Tutorial 11 | Chest Bass","channel":"SYNK","sound":"Chest Bass","difficulty":"Intermediate"},{"url":"https:\/\/www.youtube.com\/watch?v=WzCKHEUa4i4","title":"How to beatbox for beginners?- Synth Sound","channel":"Dontae Catlett","sound":"Synth Sound","difficulty":"Intermediate"},{"url":"https:\/\/www.youtube.com\/watch?v=5LiRdDjSjmM","title":"SYNTH SIREN | BEATBOX TUTORIAL","channel":"ShiroBeatbox","sound":"Synth Sound","difficulty":"Intermediate"},{"url":"https:\/\/www.youtube.com\/watch?v=2MFi5sl5jjI","title":"Tutorial #39: Synthesizer | YOU Can Beatbox","channel":"The Orthobox","sound":"Synth Sound","difficulty":"Intermediate"},{"url":"https:\/\/www.youtube.com\/watch?v=zzttIMKSEUU","title":"Beatbox Tutorial - Synth Sound - Super Simple Sound!","channel":"MVJ","sound":"Synth Sound","difficulty":"Intermediate"},{"url":"https:\/\/www.youtube.com\/watch?v=TisWdN58PFA","title":"Lip Synthesizer | Beatbox Tutorial | Explained In Detail","channel":"Cirby Beatbox","sound":"Synth Sound","difficulty":"Intermediate"},{"url":"https:\/\/www.youtube.com\/watch?v=IdMzmiv02lY","title":"SHOW GO SCRATCH \/ SYNTH | BEATBOX TUTORIAL","channel":"ShiroBeatbox","sound":"Synth Sound","difficulty":"Intermediate"},{"url":"https:\/\/www.youtube.com\/watch?v=58luYELMIJI","title":"Beatbox Tutorial - (Synthesizer Sound) Learn How to Beat Box Synth Sounds","channel":"Beatbox Tutorial","sound":"Synth Sound","difficulty":"Intermediate"},{"url":"https:\/\/www.youtube.com\/watch?v=wyIWTFv1xhI","title":"SYNTH TUTORIAL BEATBOX","channel":"Elvis Gomes","sound":"Synth Sound","difficulty":"Intermediate"},{"url":"https:\/\/www.youtube.com\/watch?v=jm-Y40uooFA","title":"Beatbox Tutorial | Show-Go Style Synth","channel":"SpaceMonk","sound":"Synth Sound","difficulty":"Intermediate"},{"url":"https:\/\/www.youtube.com\/watch?v=W-5-f2a-p-8","title":"Tutorial#22 Lazers & Synths | Kindo","channel":"Kindo Beats","sound":"Synth Sound","difficulty":"Intermediate"},{"url":"https:\/\/www.youtube.com\/watch?v=TWxrqfJN1_I","title":"MixFX - #1 Siren Roll - Beatbox Tutorial","channel":"MixFX","sound":"Synth Sound","difficulty":"Intermediate"},{"url":"https:\/\/www.youtube.com\/watch?v=4UkQQ8ASPPo","title":"Beatbox Tutorial - Duck Hi-Hat","channel":"RubikBBX","sound":"Synth Sound","difficulty":"Intermediate"},{"url":"https:\/\/www.youtube.com\/watch?v=-3cDAlUDuI0","title":"How to Beatbox (Trumpet Synth)","channel":"BestSecretsTutorials","sound":"Synth Sound","difficulty":"Intermediate"},{"url":"https:\/\/www.youtube.com\/watch?v=i_CCjEVnbdU","title":"Synth Effect | Beatbox Tutorials | Vineeth & Julius | Beatboxing for Bosses","channel":"Vineeth Vincent Official","sound":"Synth Sound","difficulty":"Intermediate"},{"url":"https:\/\/www.youtube.com\/watch?v=U1y-AyeLkcA","title":"SYNTH Sound Beatbox Tutorial in Hindi","channel":"Bbx Jeewak","sound":"Synth Sound","difficulty":"Intermediate"},{"url":"https:\/\/www.youtube.com\/watch?v=4-wrlrHIFNI","title":"Zhang Ze Synth Sound Effect Beatbox Tutorial","channel":"Alex Brothers","sound":"Synth Sound","difficulty":"Intermediate"},{"url":"https:\/\/www.youtube.com\/watch?v=cE-oPz7zK60","title":"How to beatbox for beginners?- Crab Scratch","channel":"Dontae Catlett","sound":"Crab Scratch","difficulty":"Intermediate"},{"url":"https:\/\/www.youtube.com\/watch?v=LWB3TGKV0eI","title":"Crabscratch Beatbox Tutorial","channel":"DD Beatbox","sound":"Crab Scratch","difficulty":"Intermediate"},{"url":"https:\/\/www.youtube.com\/watch?v=r0YkQ8ddUFM","title":"How to Beatbox: Air Scratch\/Handless Crab Scratch","channel":"thegroovynewts","sound":"Crab Scratch","difficulty":"Intermediate"},{"url":"https:\/\/www.youtube.com\/watch?v=H9I3ABNzn70","title":"BEATBOX EXERCICE 09 - WORK YOUR CRAB SCRATCH","channel":"ALEM\u00a0","sound":"Crab Scratch","difficulty":"Intermediate"},{"url":"https:\/\/www.youtube.com\/watch?v=PtU_ejHdOgY","title":"How to Beatbox (Crab Scratch)","channel":"BestSecretsTutorials","sound":"Crab Scratch","difficulty":"Intermediate"},{"url":"https:\/\/www.youtube.com\/watch?v=QjktzdASyn4","title":"Basic Scratch Beatbox Tutorial","channel":"Mckoy TV","sound":"Crab Scratch","difficulty":"Intermediate"},{"url":"https:\/\/www.youtube.com\/watch?v=ktBn22557Zc","title":"BEATBOXING FOR BEGINNERS | SPECIAL | CRAB SCRATCH","channel":"Faz Shah","sound":"Crab Scratch","difficulty":"Intermediate"},{"url":"https:\/\/www.youtube.com\/watch?v=_XUu5D-apbU","title":"Crab Scratch Tutorial - How To Beatbox 2020","channel":"KAO Beatbox Tutorials","sound":"Crab Scratch","difficulty":"Intermediate"},{"url":"https:\/\/www.youtube.com\/watch?v=gbxNSmIwKjY","title":"How To Beatbox - Crab Scratch","channel":"HIKAKIN\u00a0","sound":"Crab Scratch","difficulty":"Intermediate"},{"url":"https:\/\/www.youtube.com\/watch?v=O0_WzdoPr_c","title":"The Crab Scratch | Skratch School","channel":"Skratch School","sound":"Crab Scratch","difficulty":"Intermediate"},{"url":"https:\/\/www.youtube.com\/watch?v=b_YCz0s4YB4","title":"Crab Scratch Tutorial | How to Beatbox (Beatbox Tutorial) (Beatbox tagalog Version)","channel":"Jai Miss","sound":"Crab Scratch","difficulty":"Intermediate"},{"url":"https:\/\/www.youtube.com\/watch?v=AZZURbPlDiw","title":"Sophia Beatbox Tutorial 5 - Crab Scratch \/ Abra Scratch","channel":"SOPHIA BEATBOX","sound":"Crab Scratch","difficulty":"Intermediate"},{"url":"https:\/\/www.youtube.com\/watch?v=cTnih-ygv4E","title":"Learn To DJ Tutorial: How to Properly Execute the Crab Scratch (DJ Throdown)","channel":"Beat Refinery","sound":"Crab Scratch","difficulty":"Intermediate"},{"url":"https:\/\/www.youtube.com\/watch?v=7yZwMfzLElU","title":"Tutorial #23: Crab Scratch || YOU Can Beatbox Tutorial Series","channel":"The Orthobox","sound":"Crab Scratch","difficulty":"Intermediate"},{"url":"https:\/\/www.youtube.com\/watch?v=Li-MxzP8Rvk","title":"How to do the crab scratch\/abra scratch","channel":"thegroovynewts","sound":"Crab Scratch","difficulty":"Intermediate"},{"url":"https:\/\/www.youtube.com\/watch?v=ApcKIFScxzM","title":"Tutorial beatbox crab scratch","channel":"Albeat Gude","sound":"Crab Scratch","difficulty":"Intermediate"},{"url":"https:\/\/www.youtube.com\/watch?v=FdvfEEmi0YI","title":"[HINDI] Crab Scratch Beatbox Tutorial","channel":"Bbx Jeewak","sound":"Crab Scratch","difficulty":"Intermediate"},{"url":"https:\/\/www.youtube.com\/watch?v=3cImLwYsbRs","title":"How To Crab Scratch\/ DJ Scratch Like a Pro [Beatbox Tutorial]","channel":"AGR42 weeks ago105 viewsI teach what i've learned over around ","sound":"Crab Scratch","difficulty":"Intermediate"},{"url":"https:\/\/www.youtube.com\/watch?v=Gih_ijPTQuo","title":"Codfish Throat Bass Tutorial - How To Beatbox 2020","channel":"KAO Beatbox Tutorials","sound":"Throat Bass","difficulty":"Intermediate"},{"url":"https:\/\/www.youtube.com\/watch?v=HUZU6BQqVeI","title":"How To Beatbox Throat Bass in 1 Minute","channel":"Spencer X","sound":"Throat Bass","difficulty":"Intermediate"},{"url":"https:\/\/www.youtube.com\/watch?v=UZcehNWOiuY","title":"Throat Bass Tutorial - How To Beatbox 2020","channel":"KAO Beatbox Tutorials","sound":"Throat Bass","difficulty":"Intermediate"},{"url":"https:\/\/www.youtube.com\/watch?v=a2TitLyiE80","title":"How To Beatbox - Throat Bass (Tutorial)","channel":"Kevin31","sound":"Throat Bass","difficulty":"Intermediate"},{"url":"https:\/\/www.youtube.com\/watch?v=c0ETWKXEP1w","title":"Beatbox Tutorial Tuesday EP 1: Throat Bass\/Throat Singing","channel":"80Fitz\u00a0","sound":"Throat Bass","difficulty":"Intermediate"},{"url":"https:\/\/www.youtube.com\/watch?v=Jy4j7vSrDTI","title":"Throat Bass Beatbox Tutorial","channel":"Mckoy TV","sound":"Throat Bass","difficulty":"Intermediate"},{"url":"https:\/\/www.youtube.com\/watch?v=Hwp5IkFxPQc","title":"AD BEAT | Basic Beatbox Tutorial - THROAT BASS","channel":"AD BEAT","sound":"Throat Bass","difficulty":"Intermediate"},{"url":"https:\/\/www.youtube.com\/watch?v=zDmeFtaQ_Uw","title":"Throat Bass Tutorial (I'm A Beginner)","channel":"I Am Scrubs","sound":"Throat Bass","difficulty":"Intermediate"},{"url":"https:\/\/www.youtube.com\/watch?v=sglYI_tcAsk","title":"HOW TO BEATBOX #3 (Throat Bass Basics)","channel":"SoCloseToToast\u00a0","sound":"Throat Bass","difficulty":"Intermediate"},{"url":"https:\/\/www.youtube.com\/watch?v=KDlsMBMEvFU","title":"How to Beatbox - Throat Bass Tutorial (Dubstep Beatbox)","channel":"MVJ","sound":"Throat Bass","difficulty":"Intermediate"},{"url":"https:\/\/www.youtube.com\/watch?v=3PDDYl2aSjc","title":"Tutorial#19 Throat Bass | Kindo","channel":"Kindo Beats","sound":"Throat Bass","difficulty":"Intermediate"},{"url":"https:\/\/www.youtube.com\/watch?v=HAhiha-O9s0","title":"Beatbox tutorial- Throat bass","channel":"Lee doe","sound":"Throat Bass","difficulty":"Intermediate"},{"url":"https:\/\/www.youtube.com\/watch?v=aF0xkie2KIc","title":"Throat Bass Tutorial - Top 10 Tips - How To Beatbox 2020","channel":"KAO Beatbox Tutorials","sound":"Throat Bass","difficulty":"Intermediate"},{"url":"https:\/\/www.youtube.com\/watch?v=BulRXnO85hk","title":"Beatbox Tutorial - Inward Bass (UPDATED)","channel":"RubikBBX","sound":"Throat Bass","difficulty":"Intermediate"},{"url":"https:\/\/www.youtube.com\/watch?v=wxh4Nvi6S-M","title":"How to beatbox for beginners?- Throat Bass","channel":"Dontae Catlett","sound":"Throat Bass","difficulty":"Intermediate"},{"url":"https:\/\/www.youtube.com\/watch?v=ytsyEx-uRBg","title":"Beatbox Tutorial Tuesday EP 7: Throat Tapping Technique","channel":"80Fitz\u00a0","sound":"Vocal Tap","difficulty":"Intermediate"},{"url":"https:\/\/www.youtube.com\/watch?v=WaCLd2U8Z7A","title":"Beatbox Tutorial - Vocal Tap","channel":"Fat Tony","sound":"Vocal Tap","difficulty":"Intermediate"},{"url":"https:\/\/www.youtube.com\/watch?v=BZQhFfMcvt4","title":"Vocal tap - BeatBox Tutorial (by Tyte)","channel":"BeatboxBe","sound":"Vocal Tap","difficulty":"Intermediate"},{"url":"https:\/\/www.youtube.com\/watch?v=2o30SMa5uoY","title":"MTS BEATBOX - VOCAL MELODY TUTORIAL (English)","channel":"Curtis Price","sound":"Vocal Tap","difficulty":"Intermediate"},{"url":"https:\/\/www.youtube.com\/watch?v=IyUvRnrd3EA","title":"Vocal Tap","channel":"Learn to Beatbox","sound":"Vocal Tap","difficulty":"Intermediate"},{"url":"https:\/\/www.youtube.com\/watch?v=JGG-0GoFImY","title":"Beatbox Tutorial - Sucker Punch","channel":"RubikBBX","sound":"Sucker Punch","difficulty":"Intermediate"},{"url":"https:\/\/www.youtube.com\/watch?v=xdIMQaSW1zU","title":"Tutorial#12 Sucker Punch Tutorial | Kindo","channel":"Kindo Beats","sound":"Sucker Punch","difficulty":"Intermediate"},{"url":"https:\/\/www.youtube.com\/watch?v=3wYGPesUUHE","title":"Sucker Punch Tutorial - How To Beatbox 2020","channel":"KAO Beatbox Tutorials","sound":"Sucker Punch","difficulty":"Intermediate"},{"url":"https:\/\/www.youtube.com\/watch?v=MeC0LNUsDOo","title":"Sucker Punch beatbox tutorial and Beatbox patterns for beginners in Hindi","channel":"Bbx Jeewak","sound":"Sucker Punch","difficulty":"Intermediate"},{"url":"https:\/\/www.youtube.com\/watch?v=TR_3VqAxbHA","title":"BEATBOX TUTORIAL | SUCKER PUNCH","channel":"Tiny Beat","sound":"Sucker Punch","difficulty":"Intermediate"},{"url":"https:\/\/www.youtube.com\/watch?v=ipvprGFU4RM","title":"PATTERN BEAT ALEXINHO + SUCKER PUNCH !! || TUTORIAL BEATBOX","channel":"Louise Stvn","sound":"Sucker Punch","difficulty":"Intermediate"},{"url":"https:\/\/www.youtube.com\/watch?v=RAp7t_eejv4","title":"Tutorial Beatbox | Sucker Punch atau Inward Dry Kick | Ego Beatbox","channel":"Ego Firnando","sound":"Sucker Punch","difficulty":"Intermediate"},{"url":"https:\/\/www.youtube.com\/watch?v=00nJjl-tnN0","title":"Tutorial How To Beatbox \"Sucker Punch\"","channel":"Petrus Damianus","sound":"Sucker Punch","difficulty":"Intermediate"},{"url":"https:\/\/www.youtube.com\/watch?v=J1yy41OvCUY","title":"Alexinho sucker punch | Tutorial de beatbox #26 | Orodreth","channel":"Orodreth","sound":"Sucker Punch","difficulty":"Intermediate"},{"url":"https:\/\/www.youtube.com\/watch?v=2CoaHXTOUCE","title":"Beatbox Tutorial - sucker punch, villain fart bass, rolling bmg snare","channel":"Kross bbx","sound":"Sucker Punch","difficulty":"Intermediate"},{"url":"https:\/\/www.youtube.com\/watch?v=P-VLpCZYwEY","title":"How To Beatbox - Hollow Clop Tutorial","channel":"TylaDubya","sound":"Hollow Clop","difficulty":"Intermediate"},{"url":"https:\/\/www.youtube.com\/watch?v=40NGid0PLRQ","title":"Beatbox Tutorial | Hollow Clop","channel":"Mckoy TV","sound":"Hollow Clop","difficulty":"Intermediate"},{"url":"https:\/\/www.youtube.com\/watch?v=mXyhHaAqwQg","title":"Beatbox Tutorial : Hollow Clop","channel":"RubikBBX","sound":"Hollow Clop","difficulty":"Intermediate"},{"url":"https:\/\/www.youtube.com\/watch?v=jDvFbAJvez4","title":"Hollow Clop water tutorial BEatBoX","channel":"John Blue Abad","sound":"Hollow Clop","difficulty":"Intermediate"},{"url":"https:\/\/www.youtube.com\/watch?v=q3Bnc_fpEf4","title":"How To Beatbox The Hollow Clop in 1 Minute","channel":"Spencer X","sound":"Hollow Clop","difficulty":"Intermediate"},{"url":"https:\/\/www.youtube.com\/watch?v=1JvvaemKpCU","title":"Hollow Clop Beatbox Tutorial","channel":"Its the As3r","sound":"Hollow Clop","difficulty":"Intermediate"},{"url":"https:\/\/www.youtube.com\/watch?v=9Cz--KeIY-4","title":"Hollow Clop | Beatbox Tutorial | Tagalog Version","channel":"Jai Miss","sound":"Hollow Clop","difficulty":"Intermediate"},{"url":"https:\/\/www.youtube.com\/watch?v=CEG7oUnULA0","title":"Hollow Clop Tutorial | Hollow Clop Techniques Tutorial","channel":"Nemesis Music","sound":"Hollow Clop","difficulty":"Intermediate"},{"url":"https:\/\/www.youtube.com\/watch?v=7fUrE_O5B0A","title":"Beatbox Tutorial | Triple Hollow Clop","channel":"Mckoy TV","sound":"Hollow Clop","difficulty":"Intermediate"},{"url":"https:\/\/www.youtube.com\/watch?v=e75usYk9DaM","title":"How to Beatbox - Kohey GBB20 wildcard clop tutorial || Hollow Clop Beatbox tutorial","channel":"Debayan Mondal","sound":"Hollow Clop","difficulty":"Intermediate"},{"url":"https:\/\/www.youtube.com\/watch?v=pX4BoawLtyI","title":"Hollow Clop ~ Beatbox Tutorial","channel":"MisFire\u00a0","sound":"Hollow Clop","difficulty":"Intermediate"},{"url":"https:\/\/www.youtube.com\/watch?v=mPxxljMZJbc","title":"Beatbox Tutorial - Hollow Liproll Combos","channel":"RubikBBX","sound":"Hollow Clop","difficulty":"Intermediate"},{"url":"https:\/\/www.youtube.com\/watch?v=Tgak0IO0xxk","title":"Beatbox Tutorial w\/ Spencerx","channel":"Joey Klaasen\u00a0","sound":"Hollow Clop","difficulty":"Intermediate"},{"url":"https:\/\/www.youtube.com\/watch?v=dAcTTFIGC7k","title":"Triple hollow clap | Tutorial de beatbox #36 | Orodreth","channel":"Orodreth","sound":"Hollow Clop","difficulty":"Intermediate"},{"url":"https:\/\/www.youtube.com\/watch?v=OgUXmQ2bhpY","title":"Beatbox tutorial - Hollow clop","channel":"Fat Tony","sound":"Hollow Clop","difficulty":"Intermediate"},{"url":"https:\/\/www.youtube.com\/watch?v=JN-OTphL8Z0","title":"Tutorial #14: Bongo Drum\/Hollow Clop || YOU Can Beatbox Tutorial Series","channel":"The Orthobox","sound":"Hollow Clop","difficulty":"Intermediate"},{"url":"https:\/\/www.youtube.com\/watch?v=-1s_MQt6Mvo","title":"Tutorial Beatbox 13 - Clop & Hollow Clop by Jakarta Beatbox","channel":"Jakarta Beatbox\u00a0","sound":"Hollow Clop","difficulty":"Intermediate"},{"url":"https:\/\/www.youtube.com\/watch?v=8DCeax7lPZs","title":"Basic BEATBOX Tutorial #2 - Hollow Clap in TAGALOG w\/ English Subs","channel":"Madibeats","sound":"Hollow Clop","difficulty":"Intermediate"},{"url":"https:\/\/www.youtube.com\/watch?v=dB-0Q08HZk0","title":"HOW TO DO HOLLOW CLOPS [BASIC BEATBOXING TUTORIAL #4] EXPLAINED IN MOST EASIEST WAY EVER","channel":"N - Grave","sound":"Hollow Clop","difficulty":"Intermediate"},{"url":"https:\/\/www.youtube.com\/watch?v=2hNEs5VCQR8&t=5s","title":"Mouth Trumpet Tutorial -Tom Thum beatbox","channel":"Tom Thum","sound":"Trumpet","difficulty":"Intermediate"},{"url":"https:\/\/www.youtube.com\/watch?v=CdHByGZ7y8s","title":"Beatbox Tutorial Tuesday EP 10: Vocal Trumpet","channel":"80Fitz","sound":"Trumpet","difficulty":null},{"url":"https:\/\/www.youtube.com\/watch?v=BUGXjIfmra8","title":"How to do the Human Trumpet? (Everyone can do it ??)","channel":"Dharni","sound":"Trumpet","difficulty":null},{"url":"https:\/\/www.youtube.com\/watch?v=rFG-u1b-3rI","title":"Tutorial #26: Trumpet || YOU Can Beatbox","channel":"The Orthobox","sound":"Trumpet","difficulty":null},{"url":"https:\/\/www.youtube.com\/watch?v=FfIO5qr1pxM","title":"HOW TO TRUMPET BEATBOX!","channel":"SoCloseToToast\u00a0","sound":"Trumpet","difficulty":null},{"url":"https:\/\/www.youtube.com\/watch?v=l2LC450IwUQ","title":"Beatbox Tutorial Episode 10: The Trumpet Sound","channel":"Beatbox Tutorials","sound":"Trumpet","difficulty":null},{"url":"https:\/\/www.youtube.com\/watch?v=FhZL-uP9k9U","title":"Impress People With The Human Trumpet - Beatbox Tutorial","channel":"MR MiC","sound":"Trumpet","difficulty":null},{"url":"https:\/\/www.youtube.com\/watch?v=YEpFCNtjWfI","title":"How To Trumpet Sound (with English subtitles on important parts)","channel":"Mckoy TV","sound":"Trumpet","difficulty":null}]